README.md
setup.py
pyrigidbody3d/__init__.py
pyrigidbody3d/geometry.py
pyrigidbody3d/geometry_test.py
pyrigidbody3d/joint.py
pyrigidbody3d/pose.py
pyrigidbody3d/pose_test.py
pyrigidbody3d/quaternion.py
pyrigidbody3d/quaternion_test.py
pyrigidbody3d/rigidbody.py
pyrigidbody3d/rigidbody_test.py
pyrigidbody3d/world.py
pyrigidbody3d/world_example.py
pyrigidbody3d/world_test.py
pyrigidbody3d.egg-info/PKG-INFO
pyrigidbody3d.egg-info/SOURCES.txt
pyrigidbody3d.egg-info/dependency_links.txt
pyrigidbody3d.egg-info/requires.txt
pyrigidbody3d.egg-info/top_level.txt